backend.v
module backend (
    input i_clk,
    input i_resetbALL,
    input i_sclk,
    input i_sdin,
    input i_RO_clk,
    input [3:0] i_ADCout,
    
    output reg o_ready,
    output reg o_resetb_amp,
    output reg o_resetb_core,
    output reg [2:0] o_gain,
    output reg o_Ibias_2x,
    output reg o_enableRO,
    output o_core_clk
);

    reg [4:0] serBuf;             // 5 bit buffer for storing i_sdin values
    reg [2:0] cycles, count;      // Counters for counting upto 5: cycles for waiting 5 cycles, count for 5 sdin bits
    reg [1:0] clk_div;            // Counter for generating i_clk/4
    reg [11:0] ADCbuf;            // 12 bit buffer for storing i_ADC_out values of last 3 cycles
    reg [5:0] ADCsum;             // 6 bit ADCsum (4'b1111 *4 = 6'b111100)
    reg [3:0] ADCavg;

    reg [2:0] state, next;
    reg prev;

    localparam [2:0] IDLE = 0,  // Reset state
                   SERIAL = 1,  // Serial Communication on going
                    EN_RO = 2,  // Set o_enableRO
                    WAIT5 = 3,  // Waiting for 5 cycles
                  IB_CORE = 4,  // Set o_Ibias, o_core_clk
                   RESETS = 5,  // Set o_resetb_amp, o_resetb_core
                  WAIT5_2 = 6,  // Waiting for 5 cycles
                    READY = 7;
    
    // Generating i_clk/4
    always @(posedge i_clk or negedge i_resetbALL) begin
      if(!i_resetbALL) begin
        clk_div <= 0;
      end

      else begin
        clk_div <= clk_div+1;
      end
    end
    
    // Computing moving average 
    always @(posedge i_clk or negedge i_resetbALL) begin
        if(!i_resetbALL)  begin
            ADCbuf <= 12'd0;
            ADCsum <= 0;
            ADCavg <= 0;
        end
        else begin
            ADCsum <= i_ADCout + ADCbuf[11:8] + ADCbuf[7:4] + ADCbuf[3:0];
            ADCavg <= ADCsum>>2;
            ADCbuf <= {i_ADCout, ADCbuf[11:4]};
        end
    end

    // Setting o_gain, serial communication
    always @(posedge i_clk or negedge i_resetbALL) begin
        if(!i_resetbALL)  begin
            prev   <= 0;
            serBuf <= 0;
            o_gain <= 0;
            count  <= 0;
        end
        else  begin
            prev <= i_sclk;
            if({prev, i_sclk}==2'b01) begin
                serBuf <= {i_sdin, serBuf[3:0]};
                o_gain <= serBuf[4:2];
                count  <= (count==4)? 0:count+1;
            end
        end
    end

    // Setting outputs based on current state
    always @(posedge i_clk or negedge i_resetbALL)  begin
        if(!i_resetbALL) begin
            state <= IDLE;
        end

        else begin
            state <= next;
        end

        case(state)
           IDLE:  begin
                cycles <= 0;
                count  <= 0;
                o_enableRO    <= 0;
                o_resetb_amp  <= 0;
                o_resetb_core <= 0;
                o_Ibias_2x    <= 0;
                o_ready       <= 0;
           end
           SERIAL: begin
                cycles <= 0;
                o_enableRO    <= 0;
                o_resetb_amp  <= 0;
                o_resetb_core <= 0;
                o_Ibias_2x    <= 0;
                o_ready       <= 0;
           end
           EN_RO: begin
                cycles <= 0;
                count  <= 0;
                o_enableRO    <= 1;
                o_resetb_amp  <= 0;
                o_resetb_core <= 0;
                o_Ibias_2x    <= 0;
                o_ready       <= 0;
           end
           WAIT5: begin
                cycles <= cycles+1;
                count  <= 0;
                o_enableRO    <= 1;
                o_resetb_amp  <= 0;
                o_resetb_core <= 0;
                o_Ibias_2x    <= 0;
                o_ready       <= 0;
           end
           IB_CORE: begin
                cycles <= 0;
                count  <= 0;
                o_enableRO    <= 1;
                o_resetb_amp  <= 0;
                o_resetb_core <= 0;
                o_Ibias_2x    <= (ADCavg>12)? 1'b1:1'b0;
                o_ready       <= 0;
           end
           RESETS: begin
                cycles <= 0;
                count  <= 0;
                o_enableRO    <= 1;
                o_resetb_amp  <= 1;
                o_resetb_core <= 1;
                o_Ibias_2x    <= o_Ibias_2x;
                o_ready       <= 0;
           end
           WAIT5_2:  begin
                cycles <= cycles+1;
                count  <= 0;
                o_enableRO    <= 1;
                o_resetb_amp  <= 1;
                o_resetb_core <= 1;
                o_Ibias_2x    <= o_Ibias_2x;
                o_ready       <= 0;
           end
           READY:  begin
                cycles <= 0;
                count  <= 0;
                o_enableRO    <= 1;
                o_resetb_amp  <= 1;
                o_resetb_core <= 1;
                o_ready       <= 1;
                
                if(ADCavg < 8) begin
                    o_Ibias_2x <= 0;
                end
                else if(ADCavg > 12)  begin
                    o_Ibias_2x <= 1;
                end
           end
        endcase
    end

    // Next state transition logic
    always @(*)  begin
        case(state)
           IDLE   : next <= SERIAL;
           SERIAL : next <= (count==4)? EN_RO:SERIAL;
           EN_RO  : next <= WAIT5;
           WAIT5  : next <= (cycles==4)? IB_CORE:WAIT5;
           IB_CORE: next <= RESETS;
           RESETS : next <= WAIT5_2;
           WAIT5_2: next <= (cycles==4)? READY: WAIT5_2;
           READY  : next <= READY;
        endcase
    end

    assign o_core_clk = (o_Ibias_2x)? clk_div[1]:((state>WAIT5)? i_clk:1'b0);  // set o_core_clk based on o_Ibias_2x and state

endmodule

FPGA_model.v
/*FPGA model
 * Generates reset signal for the chip
 * Sends out progamming bits to the chip
*/
module FPGA_model(	i_resetbFPGA,
			i_ready,
			i_mainclk,
			o_resetbAll,
			o_sclk, 
			o_sdout);
			

//============================================================================
//Parameter declarations
parameter gainA1	= 6; //range: 0-7. Gain of amplifier 

//FPGA states
parameter sRESET 	= 0; //Reset all internal variables. Make o_resetbAll=0.
parameter sPROGRAM	= 1; //Send programming bits to chip.
parameter sIDLE		= 2; //Do nothing.
//===========================================================================
//Input output declarations
input i_resetbFPGA; 		//resets FPGA
input i_ready;			//Alerts FPGA that chip is programmed and ready
input i_mainclk;		//Main clock
output reg o_resetbAll;		//Reset for the chip
output reg o_sclk;		//Serial clock for communication
output reg o_sdout;		//Serial data out from FPGA (to chip)


//Internal wire, reg declarations
reg [1:0] FPGAstate;         //Holds the state of FPGA
reg [3:0] count;		     //Used for controlling sclk generation and transmission of serial data
reg mainclkby2, mainclkby4, mainclkby8, mainclkby16;    //Low frequency clocks derived from mainclk

//=============================================================
//BEHAVIORAL DESCRIPTION
//=============================================================
// Setting the FPGA state
always @ (posedge(i_mainclk) or negedge(i_resetbFPGA))
begin
	if(i_resetbFPGA == 0)
		FPGAstate <= sRESET;
	else
	begin
		case(FPGAstate)
		sRESET: FPGAstate <= sPROGRAM;
		sPROGRAM: 
		begin	
			if(count== 11)
				FPGAstate <= sIDLE;
			else
				FPGAstate <= sPROGRAM;
		end
		sIDLE: FPGAstate <=sIDLE;
		default: FPGAstate <= sIDLE;
		endcase
	end
end

//========================================================
/*resetbALL
 * resetbAll=0, when FPGA is reset. 
 * resetbAll=1 at all other times.
*/
always @(posedge(i_mainclk) or negedge(i_resetbFPGA))
begin
	if(i_resetbFPGA == 0)
		o_resetbAll <= 0;
	else
	begin
		if(FPGAstate == sRESET)
			o_resetbAll <= 0;
		else
			o_resetbAll <= 1;
	end
end
//==========================================================
/* Generation of low frequency clocks from mainclk using divide-by-2 method
*/
always @ (posedge(i_mainclk) or negedge(i_resetbFPGA))
begin
	if(i_resetbFPGA == 0)
		mainclkby2 <= 0;
	else
		mainclkby2 <= ~mainclkby2;
end

always @ (posedge(mainclkby2) or negedge(i_resetbFPGA))
begin
	if(i_resetbFPGA == 0)
		mainclkby4 <= 0;
	else
		mainclkby4 <= ~mainclkby4;
end

always @(posedge(mainclkby4) or negedge(i_resetbFPGA))
begin
	if(i_resetbFPGA == 0)
		mainclkby8 <= 0;
	else
		mainclkby8 <= ~mainclkby8;
end

always @(posedge(mainclkby8) or negedge(i_resetbFPGA))
begin
	if(i_resetbFPGA == 0)
		mainclkby16 <= 0;
	else
		mainclkby16 <= ~mainclkby16;
end
//==========================================================
/*count
 * used for the generation of sclk and selecting the data to be sent in through sdin
 */
always	@(posedge(mainclkby16) or negedge(i_resetbFPGA))
begin
	if(i_resetbFPGA == 0)
		count <= 0;
	else
	begin
		if(FPGAstate == sPROGRAM)
		begin
			if(count == 11)
				count <= count;
			else
				count <= count+1;
		end
		else
			count <= count;
	end
end
//=========================================================
/*sclk
 * sclk is a clock only when the FPGA is programming the chip.
 */
always @ (posedge(mainclkby16) or negedge(i_resetbFPGA))
begin
	if(i_resetbFPGA == 0)
		o_sclk <= 1;
	else
	begin
		if(FPGAstate == sPROGRAM)
		begin
			if (count >= 1 && count <= 10)
				o_sclk <= ~o_sclk;
			else
				o_sclk <= 1;
		end
		else
			o_sclk <= 1;
	end
end

//=========================================================
/*sdin
 *serial data out from FPGA
 */
always @ (negedge(o_sclk) or negedge(i_resetbFPGA))
begin
	if(i_resetbFPGA == 0)
		o_sdout <= 0;
	else
	begin
		if(FPGAstate == sPROGRAM)
		begin
			case(count)
			4'd2: o_sdout <= 0;
			4'd4: o_sdout <= 0;
			4'd6: o_sdout <= gainA1[2];
			4'd8: o_sdout <= gainA1[1];
			4'd10: o_sdout <= gainA1[0];
			default: o_sdout <= o_sdout;
			endcase
		end
		else
			o_sdout <= 0;
		
	end
end

//==========================================================
endmodule

backend_tb.v
// Testbanch module for the backend. This has a module instantiation for
// the FPGA_model and the backend.
`timescale 1ns / 1ps
//==========================================================================
//Change the Verilog filenames approppriately.
`include "FPGA_model.v"
`include "backend.v"
//=========================================================================

module backend_tb();

reg resetbFPGA;
reg main_clk;
reg RO_clock_model; 
reg [3:0]ADCout;

wire [2:0]gainA1 ;
wire resetb_core;
wire resetbAll, resetb_amp,  enableRO; 
wire core_clk,RO_clk ;
wire sclk, sdin;
wire ready;
wire Ibias_2x;


//==========================================================================
//FPGA model instantiation
FPGA_model   FPGA_obj(	.i_resetbFPGA (resetbFPGA),
			.i_ready (ready),
			.o_resetbAll (resetbAll),
			.i_mainclk (main_clk),
			.o_sclk (sclk), 
			.o_sdout (sdin) );

// Backend instantiation 
backend backend_obj (	.i_resetbALL (resetbAll),
			.i_clk (main_clk),
			.i_sclk (sclk),
			.i_sdin (sdin),
			.i_RO_clk (RO_clk), 
			.i_ADCout(ADCout),
			.o_Ibias_2x (Ibias_2x),
			.o_core_clk  (core_clk ),
			.o_ready (ready),
			.o_resetb_amp (resetb_amp),
			.o_gain (gainA1),
			.o_enableRO (enableRO),
			.o_resetb_core (resetb_core) );
//============================================================================
// VCO clock model
assign RO_clk = (enableRO)?RO_clock_model:0;

initial
begin
$dumpfile ("comp.vcd") ;
$dumpvars (0, backend_tb) ;

end
//============================================================================

//Test signal generation
initial
begin
	resetbFPGA <= 0;
	main_clk <= 0;
	RO_clock_model <= 0;
	ADCout<= 1;

	#10 resetbFPGA <= 1;
	//#50 resetbFPGA <= 0;
	#20000;
	$finish;
	
end

//Generation of main_clk 
always #2 main_clk <= ~main_clk;

//Generation of internal clock models for the VCOs
always #0.5 RO_clock_model <= ~RO_clock_model;//1GHz, Range: 500MHz to 1.5GHz)

//============================================================================
endmodule

comp.vcd
$date
	Sun May 11 16:56:51 2025
$end
$version
	Icarus Verilog
$end
$timescale
	1ps
$end
$scope module backend_tb $end
$var wire 1 ! sdin $end
$var wire 1 " sclk $end
$var wire 1 # resetb_core $end
$var wire 1 $ resetb_amp $end
$var wire 1 % resetbAll $end
$var wire 1 & ready $end
$var wire 3 ' gainA1 [2:0] $end
$var wire 1 ( enableRO $end
$var wire 1 ) core_clk $end
$var wire 1 * RO_clk $end
$var wire 1 + Ibias_2x $end
$var reg 4 , ADCout [3:0] $end
$var reg 1 - RO_clock_model $end
$var reg 1 . main_clk $end
$var reg 1 / resetbFPGA $end
$scope module FPGA_obj $end
$var wire 1 . i_mainclk $end
$var wire 1 / i_resetbFPGA $end
$var wire 1 & i_ready $end
$var parameter 32 0 gainA1 $end
$var parameter 32 1 sIDLE $end
$var parameter 32 2 sPROGRAM $end
$var parameter 32 3 sRESET $end
$var reg 2 4 FPGAstate [1:0] $end
$var reg 4 5 count [3:0] $end
$var reg 1 6 mainclkby16 $end
$var reg 1 7 mainclkby2 $end
$var reg 1 8 mainclkby4 $end
$var reg 1 9 mainclkby8 $end
$var reg 1 % o_resetbAll $end
$var reg 1 " o_sclk $end
$var reg 1 ! o_sdout $end
$upscope $end
$scope module backend_obj $end
$var wire 4 : i_ADCout [3:0] $end
$var wire 1 * i_RO_clk $end
$var wire 1 . i_clk $end
$var wire 1 % i_resetbALL $end
$var wire 1 " i_sclk $end
$var wire 1 ! i_sdin $end
$var wire 1 ) o_core_clk $end
$var parameter 3 ; EN_RO $end
$var parameter 3 < IB_CORE $end
$var parameter 3 = IDLE $end
$var parameter 3 > READY $end
$var parameter 3 ? RESETS $end
$var parameter 3 @ SERIAL $end
$var parameter 3 A WAIT5 $end
$var parameter 3 B WAIT5_2 $end
$var reg 4 C ADCavg [3:0] $end
$var reg 12 D ADCbuf [11:0] $end
$var reg 6 E ADCsum [5:0] $end
$var reg 2 F clk_div [1:0] $end
$var reg 3 G count [2:0] $end
$var reg 3 H cycles [2:0] $end
$var reg 3 I next [2:0] $end
$var reg 1 + o_Ibias_2x $end
$var reg 1 ( o_enableRO $end
$var reg 3 J o_gain [2:0] $end
$var reg 1 & o_ready $end
$var reg 1 $ o_resetb_amp $end
$var reg 1 # o_resetb_core $end
$var reg 1 K prev $end
$var reg 5 L serBuf [4:0] $end
$var reg 3 M state [2:0] $end
$upscope $end
$upscope $end
$enddefinitions $end
$comment Show the parameter values. $end
$dumpall
b110 B
b11 A
b1 @
b101 ?
b111 >
b0 =
b100 <
b10 ;
b0 3
b1 2
b10 1
b110 0
$end
#0
$dumpvars
b0 M
b0 L
0K
b0 J
b1 I
bx H
b0 G
b0 F
b0 E
b0 D
b0 C
b1 :
09
08
07
06
b0 5
b0 4
0/
0.
0-
b1 ,
x+
0*
0)
x(
b0 '
x&
0%
x$
x#
1"
0!
$end
#500
x*
1-
#1000
0*
0-
#1500
x*
1-
#2000
0&
0+
0#
0$
0(
b0 H
0*
0-
1.
#2500
1-
#3000
0-
#3500
1-
#4000
0-
0.
#4500
1-
#5000
0-
#5500
1-
#6000
0-
1.
#6500
1-
#7000
0-
#7500
1-
#8000
0-
0.
#8500
1-
#9000
0-
#9500
1-
#10000
b1 5
16
19
18
17
b1 4
0-
1.
1/
#10500
1-
#11000
0-
#11500
1-
#12000
0-
0.
#12500
1-
#13000
0-
#13500
1-
#14000
1%
07
0-
1.
#14500
1-
#15000
0-
#15500
1-
#16000
0-
0.
#16500
1-
#17000
0-
#17500
1-
#18000
08
17
b1 M
b0 G
1K
b100000000 D
b1 E
b1 F
0-
1.
#18500
1-
#19000
0-
#19500
1-
#20000
0-
0.
#20500
1-
#21000
0-
#21500
1-
#22000
07
b10 F
b100010000 D
b10 E
0-
1.
#22500
1-
#23000
0-
#23500
1-
#24000
0-
0.
#24500
1-
#25000
0-
#25500
1-
#26000
09
18
17
b100010001 D
b11 E
b11 F
0-
1.
#26500
1-
#27000
0-
#27500
1-
#28000
0-
0.
#28500
1-
#29000
0-
#29500
1-
#30000
07
b0 F
b100 E
0-
1.
#30500
1-
#31000
0-
#31500
1-
#32000
0-
0.
#32500
1-
#33000
0-
#33500
1-
#34000
08
17
b1 C
b1 F
0-
1.
#34500
1-
#35000
0-
#35500
1-
#36000
0-
0.
#36500
1-
#37000
0-
#37500
1-
#38000
07
b10 F
0-
1.
#38500
1-
#39000
0-
#39500
1-
#40000
0-
0.
#40500
1-
#41000
0-
#41500
1-
#42000
06
19
18
17
b11 F
0-
1.
#42500
1-
#43000
0-
#43500
1-
#44000
0-
0.
#44500
1-
#45000
0-
#45500
1-
#46000
07
b0 F
0-
1.
#46500
1-
#47000
0-
#47500
1-
#48000
0-
0.
#48500
1-
#49000
0-
#49500
1-
#50000
08
17
b1 F
0-
1.
#50500
1-
#51000
0-
#51500
1-
#52000
0-
0.
#52500
1-
#53000
0-
#53500
1-
#54000
07
b10 F
0-
1.
#54500
1-
#55000
0-
#55500
1-
#56000
0-
0.
#56500
1-
#57000
0-
#57500
1-
#58000
09
18
17
b11 F
0-
1.
#58500
1-
#59000
0-
#59500
1-
#60000
0-
0.
#60500
1-
#61000
0-
#61500
1-
#62000
07
b0 F
0-
1.
#62500
1-
#63000
0-
#63500
1-
#64000
0-
0.
#64500
1-
#65000
0-
#65500
1-
#66000
08
17
b1 F
0-
1.
#66500
1-
#67000
0-
#67500
1-
#68000
0-
0.
#68500
1-
#69000
0-
#69500
1-
#70000
07
b10 F
0-
1.
#70500
1-
#71000
0-
#71500
1-
#72000
0-
0.
#72500
1-
#73000
0-
#73500
1-
#74000
b10 5
0"
16
19
18
17
b11 F
0-
1.
#74500
1-
#75000
0-
#75500
1-
#76000
0-
0.
#76500
1-
#77000
0-
#77500
1-
#78000
07
b0 F
0K
0-
1.
#78500
1-
#79000
0-
#79500
1-
#80000
0-
0.
#80500
1-
#81000
0-
#81500
1-
#82000
08
17
b1 F
0-
1.
#82500
1-
#83000
0-
#83500
1-
#84000
0-
0.
#84500
1-
#85000
0-
#85500
1-
#86000
07
b10 F
0-
1.
#86500
1-
#87000
0-
#87500
1-
#88000
0-
0.
#88500
1-
#89000
0-
#89500
1-
#90000
09
18
17
b11 F
0-
1.
#90500
1-
#91000
0-
#91500
1-
#92000
0-
0.
#92500
1-
#93000
0-
#93500
1-
#94000
07
b0 F
0-
1.
#94500
1-
#95000
0-
#95500
1-
#96000
0-
0.
#96500
1-
#97000
0-
#97500
1-
#98000
08
17
b1 F
0-
1.
#98500
1-
#99000
0-
#99500
1-
#100000
0-
0.
#100500
1-
#101000
0-
#101500
1-
#102000
07
b10 F
0-
1.
#102500
1-
#103000
0-
#103500
1-
#104000
0-
0.
#104500
1-
#105000
0-
#105500
1-
#106000
06
19
18
17
b11 F
0-
1.
#106500
1-
#107000
0-
#107500
1-
#108000
0-
0.
#108500
1-
#109000
0-
#109500
1-
#110000
07
b0 F
0-
1.
#110500
1-
#111000
0-
#111500
1-
#112000
0-
0.
#112500
1-
#113000
0-
#113500
1-
#114000
08
17
b1 F
0-
1.
#114500
1-
#115000
0-
#115500
1-
#116000
0-
0.
#116500
1-
#117000
0-
#117500
1-
#118000
07
b10 F
0-
1.
#118500
1-
#119000
0-
#119500
1-
#120000
0-
0.
#120500
1-
#121000
0-
#121500
1-
#122000
09
18
17
b11 F
0-
1.
#122500
1-
#123000
0-
#123500
1-
#124000
0-
0.
#124500
1-
#125000
0-
#125500
1-
#126000
07
b0 F
0-
1.
#126500
1-
#127000
0-
#127500
1-
#128000
0-
0.
#128500
1-
#129000
0-
#129500
1-
#130000
08
17
b1 F
0-
1.
#130500
1-
#131000
0-
#131500
1-
#132000
0-
0.
#132500
1-
#133000
0-
#133500
1-
#134000
07
b10 F
0-
1.
#134500
1-
#135000
0-
#135500
1-
#136000
0-
0.
#136500
1-
#137000
0-
#137500
1-
#138000
1"
b11 5
16
19
18
17
b11 F
0-
1.
#138500
1-
#139000
0-
#139500
1-
#140000
0-
0.
#140500
1-
#141000
0-
#141500
1-
#142000
07
b0 F
b1 G
1K
0-
1.
#142500
1-
#143000
0-
#143500
1-
#144000
0-
0.
#144500
1-
#145000
0-
#145500
1-
#146000
08
17
b1 F
0-
1.
#146500
1-
#147000
0-
#147500
1-
#148000
0-
0.
#148500
1-
#149000
0-
#149500
1-
#150000
07
b10 F
0-
1.
#150500
1-
#151000
0-
#151500
1-
#152000
0-
0.
#152500
1-
#153000
0-
#153500
1-
#154000
09
18
17
b11 F
0-
1.
#154500
1-
#155000
0-
#155500
1-
#156000
0-
0.
#156500
1-
#157000
0-
#157500
1-
#158000
07
b0 F
0-
1.
#158500
1-
#159000
0-
#159500
1-
#160000
0-
0.
#160500
1-
#161000
0-
#161500
1-
#162000
08
17
b1 F
0-
1.
#162500
1-
#163000
0-
#163500
1-
#164000
0-
0.
#164500
1-
#165000
0-
#165500
1-
#166000
07
b10 F
0-
1.
#166500
1-
#167000
0-
#167500
1-
#168000
0-
0.
#168500
1-
#169000
0-
#169500
1-
#170000
06
19
18
17
b11 F
0-
1.
#170500
1-
#171000
0-
#171500
1-
#172000
0-
0.
#172500
1-
#173000
0-
#173500
1-
#174000
07
b0 F
0-
1.
#174500
1-
#175000
0-
#175500
1-
#176000
0-
0.
#176500
1-
#177000
0-
#177500
1-
#178000
08
17
b1 F
0-
1.
#178500
1-
#179000
0-
#179500
1-
#180000
0-
0.
#180500
1-
#181000
0-
#181500
1-
#182000
07
b10 F
0-
1.
#182500
1-
#183000
0-
#183500
1-
#184000
0-
0.
#184500
1-
#185000
0-
#185500
1-
#186000
09
18
17
b11 F
0-
1.
#186500
1-
#187000
0-
#187500
1-
#188000
0-
0.
#188500
1-
#189000
0-
#189500
1-
#190000
07
b0 F
0-
1.
#190500
1-
#191000
0-
#191500
1-
#192000
0-
0.
#192500
1-
#193000
0-
#193500
1-
#194000
08
17
b1 F
0-
1.
#194500
1-
#195000
0-
#195500
1-
#196000
0-
0.
#196500
1-
#197000
0-
#197500
1-
#198000
07
b10 F
0-
1.
#198500
1-
#199000
0-
#199500
1-
#200000
0-
0.
#200500
1-
#201000
0-
#201500
1-
#202000
b100 5
0"
16
19
18
17
b11 F
0-
1.
#202500
1-
#203000
0-
#203500
1-
#204000
0-
0.
#204500
1-
#205000
0-
#205500
1-
#206000
07
b0 F
0K
0-
1.
#206500
1-
#207000
0-
#207500
1-
#208000
0-
0.
#208500
1-
#209000
0-
#209500
1-
#210000
08
17
b1 F
0-
1.
#210500
1-
#211000
0-
#211500
1-
#212000
0-
0.
#212500
1-
#213000
0-
#213500
1-
#214000
07
b10 F
0-
1.
#214500
1-
#215000
0-
#215500
1-
#216000
0-
0.
#216500
1-
#217000
0-
#217500
1-
#218000
09
18
17
b11 F
0-
1.
#218500
1-
#219000
0-
#219500
1-
#220000
0-
0.
#220500
1-
#221000
0-
#221500
1-
#222000
07
b0 F
0-
1.
#222500
1-
#223000
0-
#223500
1-
#224000
0-
0.
#224500
1-
#225000
0-
#225500
1-
#226000
08
17
b1 F
0-
1.
#226500
1-
#227000
0-
#227500
1-
#228000
0-
0.
#228500
1-
#229000
0-
#229500
1-
#230000
07
b10 F
0-
1.
#230500
1-
#231000
0-
#231500
1-
#232000
0-
0.
#232500
1-
#233000
0-
#233500
1-
#234000
06
19
18
17
b11 F
0-
1.
#234500
1-
#235000
0-
#235500
1-
#236000
0-
0.
#236500
1-
#237000
0-
#237500
1-
#238000
07
b0 F
0-
1.
#238500
1-
#239000
0-
#239500
1-
#240000
0-
0.
#240500
1-
#241000
0-
#241500
1-
#242000
08
17
b1 F
0-
1.
#242500
1-
#243000
0-
#243500
1-
#244000
0-
0.
#244500
1-
#245000
0-
#245500
1-
#246000
07
b10 F
0-
1.
#246500
1-
#247000
0-
#247500
1-
#248000
0-
0.
#248500
1-
#249000
0-
#249500
1-
#250000
09
18
17
b11 F
0-
1.
#250500
1-
#251000
0-
#251500
1-
#252000
0-
0.
#252500
1-
#253000
0-
#253500
1-
#254000
07
b0 F
0-
1.
#254500
1-
#255000
0-
#255500
1-
#256000
0-
0.
#256500
1-
#257000
0-
#257500
1-
#258000
08
17
b1 F
0-
1.
#258500
1-
#259000
0-
#259500
1-
#260000
0-
0.
#260500
1-
#261000
0-
#261500
1-
#262000
07
b10 F
0-
1.
#262500
1-
#263000
0-
#263500
1-
#264000
0-
0.
#264500
1-
#265000
0-
#265500
1-
#266000
1"
b101 5
16
19
18
17
b11 F
0-
1.
#266500
1-
#267000
0-
#267500
1-
#268000
0-
0.
#268500
1-
#269000
0-
#269500
1-
#270000
07
b0 F
b10 G
1K
0-
1.
#270500
1-
#271000
0-
#271500
1-
#272000
0-
0.
#272500
1-
#273000
0-
#273500
1-
#274000
08
17
b1 F
0-
1.
#274500
1-
#275000
0-
#275500
1-
#276000
0-
0.
#276500
1-
#277000
0-
#277500
1-
#278000
07
b10 F
0-
1.
#278500
1-
#279000
0-
#279500
1-
#280000
0-
0.
#280500
1-
#281000
0-
#281500
1-
#282000
09
18
17
b11 F
0-
1.
#282500
1-
#283000
0-
#283500
1-
#284000
0-
0.
#284500
1-
#285000
0-
#285500
1-
#286000
07
b0 F
0-
1.
#286500
1-
#287000
0-
#287500
1-
#288000
0-
0.
#288500
1-
#289000
0-
#289500
1-
#290000
08
17
b1 F
0-
1.
#290500
1-
#291000
0-
#291500
1-
#292000
0-
0.
#292500
1-
#293000
0-
#293500
1-
#294000
07
b10 F
0-
1.
#294500
1-
#295000
0-
#295500
1-
#296000
0-
0.
#296500
1-
#297000
0-
#297500
1-
#298000
06
19
18
17
b11 F
0-
1.
#298500
1-
#299000
0-
#299500
1-
#300000
0-
0.
#300500
1-
#301000
0-
#301500
1-
#302000
07
b0 F
0-
1.
#302500
1-
#303000
0-
#303500
1-
#304000
0-
0.
#304500
1-
#305000
0-
#305500
1-
#306000
08
17
b1 F
0-
1.
#306500
1-
#307000
0-
#307500
1-
#308000
0-
0.
#308500
1-
#309000
0-
#309500
1-
#310000
07
b10 F
0-
1.
#310500
1-
#311000
0-
#311500
1-
#312000
0-
0.
#312500
1-
#313000
0-
#313500
1-
#314000
09
18
17
b11 F
0-
1.
#314500
1-
#315000
0-
#315500
1-
#316000
0-
0.
#316500
1-
#317000
0-
#317500
1-
#318000
07
b0 F
0-
1.
#318500
1-
#319000
0-
#319500
1-
#320000
0-
0.
#320500
1-
#321000
0-
#321500
1-
#322000
08
17
b1 F
0-
1.
#322500
1-
#323000
0-
#323500
1-
#324000
0-
0.
#324500
1-
#325000
0-
#325500
1-
#326000
07
b10 F
0-
1.
#326500
1-
#327000
0-
#327500
1-
#328000
0-
0.
#328500
1-
#329000
0-
#329500
1-
#330000
1!
b110 5
0"
16
19
18
17
b11 F
0-
1.
#330500
1-
#331000
0-
#331500
1-
#332000
0-
0.
#332500
1-
#333000
0-
#333500
1-
#334000
07
b0 F
0K
0-
1.
#334500
1-
#335000
0-
#335500
1-
#336000
0-
0.
#336500
1-
#337000
0-
#337500
1-
#338000
08
17
b1 F
0-
1.
#338500
1-
#339000
0-
#339500
1-
#340000
0-
0.
#340500
1-
#341000
0-
#341500
1-
#342000
07
b10 F
0-
1.
#342500
1-
#343000
0-
#343500
1-
#344000
0-
0.
#344500
1-
#345000
0-
#345500
1-
#346000
09
18
17
b11 F
0-
1.
#346500
1-
#347000
0-
#347500
1-
#348000
0-
0.
#348500
1-
#349000
0-
#349500
1-
#350000
07
b0 F
0-
1.
#350500
1-
#351000
0-
#351500
1-
#352000
0-
0.
#352500
1-
#353000
0-
#353500
1-
#354000
08
17
b1 F
0-
1.
#354500
1-
#355000
0-
#355500
1-
#356000
0-
0.
#356500
1-
#357000
0-
#357500
1-
#358000
07
b10 F
0-
1.
#358500
1-
#359000
0-
#359500
1-
#360000
0-
0.
#360500
1-
#361000
0-
#361500
1-
#362000
06
19
18
17
b11 F
0-
1.
#362500
1-
#363000
0-
#363500
1-
#364000
0-
0.
#364500
1-
#365000
0-
#365500
1-
#366000
07
b0 F
0-
1.
#366500
1-
#367000
0-
#367500
1-
#368000
0-
0.
#368500
1-
#369000
0-
#369500
1-
#370000
08
17
b1 F
0-
1.
#370500
1-
#371000
0-
#371500
1-
#372000
0-
0.
#372500
1-
#373000
0-
#373500
1-
#374000
07
b10 F
0-
1.
#374500
1-
#375000
0-
#375500
1-
#376000
0-
0.
#376500
1-
#377000
0-
#377500
1-
#378000
09
18
17
b11 F
0-
1.
#378500
1-
#379000
0-
#379500
1-
#380000
0-
0.
#380500
1-
#381000
0-
#381500
1-
#382000
07
b0 F
0-
1.
#382500
1-
#383000
0-
#383500
1-
#384000
0-
0.
#384500
1-
#385000
0-
#385500
1-
#386000
08
17
b1 F
0-
1.
#386500
1-
#387000
0-
#387500
1-
#388000
0-
0.
#388500
1-
#389000
0-
#389500
1-
#390000
07
b10 F
0-
1.
#390500
1-
#391000
0-
#391500
1-
#392000
0-
0.
#392500
1-
#393000
0-
#393500
1-
#394000
1"
b111 5
16
19
18
17
b11 F
0-
1.
#394500
1-
#395000
0-
#395500
1-
#396000
0-
0.
#396500
1-
#397000
0-
#397500
1-
#398000
07
b0 F
b11 G
b10000 L
1K
0-
1.
#398500
1-
#399000
0-
#399500
1-
#400000
0-
0.
#400500
1-
#401000
0-
#401500
1-
#402000
08
17
b1 F
0-
1.
#402500
1-
#403000
0-
#403500
1-
#404000
0-
0.
#404500
1-
#405000
0-
#405500
1-
#406000
07
b10 F
0-
1.
#406500
1-
#407000
0-
#407500
1-
#408000
0-
0.
#408500
1-
#409000
0-
#409500
1-
#410000
09
18
17
b11 F
0-
1.
#410500
1-
#411000
0-
#411500
1-
#412000
0-
0.
#412500
1-
#413000
0-
#413500
1-
#414000
07
b0 F
0-
1.
#414500
1-
#415000
0-
#415500
1-
#416000
0-
0.
#416500
1-
#417000
0-
#417500
1-
#418000
08
17
b1 F
0-
1.
#418500
1-
#419000
0-
#419500
1-
#420000
0-
0.
#420500
1-
#421000
0-
#421500
1-
#422000
07
b10 F
0-
1.
#422500
1-
#423000
0-
#423500
1-
#424000
0-
0.
#424500
1-
#425000
0-
#425500
1-
#426000
06
19
18
17
b11 F
0-
1.
#426500
1-
#427000
0-
#427500
1-
#428000
0-
0.
#428500
1-
#429000
0-
#429500
1-
#430000
07
b0 F
0-
1.
#430500
1-
#431000
0-
#431500
1-
#432000
0-
0.
#432500
1-
#433000
0-
#433500
1-
#434000
08
17
b1 F
0-
1.
#434500
1-
#435000
0-
#435500
1-
#436000
0-
0.
#436500
1-
#437000
0-
#437500
1-
#438000
07
b10 F
0-
1.
#438500
1-
#439000
0-
#439500
1-
#440000
0-
0.
#440500
1-
#441000
0-
#441500
1-
#442000
09
18
17
b11 F
0-
1.
#442500
1-
#443000
0-
#443500
1-
#444000
0-
0.
#444500
1-
#445000
0-
#445500
1-
#446000
07
b0 F
0-
1.
#446500
1-
#447000
0-
#447500
1-
#448000
0-
0.
#448500
1-
#449000
0-
#449500
1-
#450000
08
17
b1 F
0-
1.
#450500
1-
#451000
0-
#451500
1-
#452000
0-
0.
#452500
1-
#453000
0-
#453500
1-
